pixelfed_python_api/__init__.py
pixelfed_python_api/pixelfed.py
pixelfed_python_api-0.0.1.dist-info/LICENSE.txt
pixelfed_python_api-0.0.1.dist-info/METADATA
pixelfed_python_api-0.0.1.dist-info/WHEEL
pixelfed_python_api-0.0.1.dist-info/top_level.txt
pixelfed_python_api-0.0.1.dist-info/RECORD
