Metadata-Version: 2.1
Name: pixelfed-python-api
Version: 0.0.1
Summary: Python Library for Pixelfed
Author-email: Denis Cappellin <basset08.velars@icloud.com>
License: AGPL-3.0 license
Project-URL: Homepage, https://github.com/dcappellin/pixelfed-python-api
Keywords: pixelfed,python,api
Classifier: Programming Language :: Python :: 3
Classifier: Operating System :: OS Independent
Requires-Python: >=3.7
License-File: LICENSE.txt
Requires-Dist: requests
